tinderdata/__init__.py
tinderdata/__main__.py
tinderdata/context.py
tinderdata/settings.py
tinderdata/tinder.py
tinderdata/utils.py
tinderdata-0.4.2.dist-info/METADATA
tinderdata-0.4.2.dist-info/WHEEL
tinderdata-0.4.2.dist-info/licenses/LICENSE
tinderdata-0.4.2.dist-info/RECORD
