Metadata-Version: 2.3
Name: tinderdata
Version: 0.4.2
Summary: A silly utility to explore your Tinder data.
Project-URL: homepage, https://github.com/fsoubelet/Tinder_Data
Project-URL: repository, https://github.com/fsoubelet/Tinder_Data
Author-email: Felix Soubelet <felix.soubelet@cern.ch>
License-Expression: MIT
License-File: LICENSE
Keywords: Utility,Visualisation
Classifier: Development Status :: 4 - Beta
Classifier: License :: OSI Approved :: MIT License
Classifier: Natural Language :: English
Classifier: Programming Language :: Python
Classifier: Programming Language :: Python :: 3 :: Only
Classifier: Programming Language :: Python :: 3.9
Classifier: Programming Language :: Python :: 3.10
Classifier: Programming Language :: Python :: 3.11
Classifier: Programming Language :: Python :: 3.12
Classifier: Programming Language :: Python :: Implementation :: CPython
Classifier: Topic :: Scientific/Engineering :: Visualization
Classifier: Topic :: Utilities
Classifier: Typing :: Typed
Requires-Python: >=3.9
Requires-Dist: loguru<1.0
Requires-Dist: matplotlib>=3.8
Requires-Dist: pandas>=2.1
Requires-Dist: seaborn>=0.12
Requires-Dist: typer>=0.10
